MANIFEST.in
README.md
setup.cfg
setup.py
ipylogging/__init__.py
ipylogging/handler.py
ipylogging/utils.py
ipylogging.egg-info/PKG-INFO
ipylogging.egg-info/SOURCES.txt
ipylogging.egg-info/dependency_links.txt
ipylogging.egg-info/top_level.txt