Metadata-Version: 2.1
Name: ipylogging
Version: 2020.342.0
Summary: Easy log messages in Jupyter notebooks.
Home-page: https://github.com/nbgallery/ipylogging
Author: Bill Allen
Author-email: photo.allen@gmail.com
License: MIT
Keywords: logging,logger,logs,ipython,jupyter,notebook,messages
Platform: UNKNOWN
Classifier: Development Status :: 4 - Beta
Classifier: Topic :: Utilities
Classifier: License :: OSI Approved :: MIT License
